izmiran/__init__.py
izmiran/datfile.py
izmiran-0.1.2.dist-info/LICENSE
izmiran-0.1.2.dist-info/METADATA
izmiran-0.1.2.dist-info/WHEEL
izmiran-0.1.2.dist-info/top_level.txt
izmiran-0.1.2.dist-info/RECORD
