Metadata-Version: 2.1
Name: izmiran
Version: 0.1.2
Summary: IZMIRAN module for common tasks
Author-email: Danil Borchevkin <danil.borchevkin@gmail.com>
License: BSD 2-Clause License
Classifier: Development Status :: 4 - Beta
Classifier: License :: OSI Approved :: BSD License
Classifier: Programming Language :: Python :: 3
Requires-Python: >=3.7
License-File: LICENSE
